ir/Type.py
ir/__init__.py
ir/py.typed
ir/reader.py
ir/utils.py
ir/writer.py
klvm_tools/NodePath.py
klvm_tools/__init__.py
klvm_tools/binutils.py
klvm_tools/cmds.py
klvm_tools/curry.py
klvm_tools/debug.py
klvm_tools/klvmc.py
klvm_tools/operator_dict.py
klvm_tools/pattern_match.py
klvm_tools/py.typed
klvm_tools/sha256tree.py
klvm_tools/setuptools/__init__.py
klvm_tools/setuptools/build_klvm.py
klvm_tools/setuptools/patch_build_ext.py
klvm_tools/setuptools/patched_build_ext.py
stages/__init__.py
stages/py.typed
stages/stage_0.py
stages/stage_2/__init__.py
stages/stage_2/bindings.py
stages/stage_2/compile.py
stages/stage_2/defaults.py
stages/stage_2/helpers.py
stages/stage_2/mod.py
stages/stage_2/operators.py
stages/stage_2/optimize.py
klvm_tools-0.4.10.dist-info/LICENSE
klvm_tools-0.4.10.dist-info/METADATA
klvm_tools-0.4.10.dist-info/WHEEL
klvm_tools-0.4.10.dist-info/entry_points.txt
klvm_tools-0.4.10.dist-info/top_level.txt
klvm_tools-0.4.10.dist-info/RECORD
