Metadata-Version: 2.2
Name: klvm_tools
Version: 0.4.10
Summary: KLVM compiler.
Home-page: https://github.com/Chik-Network
Author: Chik Network, Inc.
Author-email: hello@chiknetwork.com
License: Apache-2.0
Project-URL: Bug Reports, https://github.com/Chik-Network/klvm_tools
Project-URL: Source, https://github.com/Chik-Network/klvm_tools
Classifier: Development Status :: 3 - Alpha
Classifier: Programming Language :: Python :: 3
Classifier: Programming Language :: Python :: 3.9
Classifier: Programming Language :: Python :: 3.10
Classifier: Programming Language :: Python :: 3.11
Classifier: Programming Language :: Python :: 3.12
Classifier: License :: OSI Approved :: Apache Software License
Classifier: Topic :: Security :: Cryptography
License-File: LICENSE
Requires-Dist: klvm>=0.9.2
Requires-Dist: klvm_tools_rs>=0.1.37
Requires-Dist: importlib_metadata
Requires-Dist: setuptools
Provides-Extra: dev
Requires-Dist: pytest; extra == "dev"
Dynamic: author
Dynamic: author-email
Dynamic: classifier
Dynamic: description
Dynamic: description-content-type
Dynamic: home-page
Dynamic: license
Dynamic: project-url
Dynamic: provides-extra
Dynamic: requires-dist
Dynamic: summary
